djangocms_custommenu/__init__.py
djangocms_custommenu/cms_plugins.py
djangocms_custommenu/models.py
djangocms_custommenu/migrations/0001_initial.py
djangocms_custommenu/migrations/0002_stylemenu.py
djangocms_custommenu/migrations/0003_stylemenu_configuration.py
djangocms_custommenu/migrations/0004_auto_20180220_0908.py
djangocms_custommenu/migrations/0005_auto_20180220_0912.py
djangocms_custommenu/migrations/0006_auto_20180220_1039.py
djangocms_custommenu/migrations/0007_auto_20180220_1247.py
djangocms_custommenu/migrations/0008_auto_20180220_2242.py
djangocms_custommenu/migrations/0009_custommenu.py
djangocms_custommenu/migrations/0010_auto_20180304_2254.py
djangocms_custommenu/migrations/__init__.py
djangocms_custommenu/templates/djangocms_custommenu/automenu/default.html
djangocms_custommenu/templates/djangocms_custommenu/breadcrumbs/default.html
djangocms_custommenu/templates/djangocms_custommenu/custommenu/base.html
djangocms_custommenu/templates/djangocms_custommenu/custommenu/default.html
djangocms_custommenu/templates/djangocms_custommenu/custommenu/show_menu.html
djangocms_custommenu/templates/djangocms_custommenu/custommenu/show_menu_below_id.html
djangocms_custommenu/templates/djangocms_custommenu/custommenu/show_sub_menu.html
djangocms_custommenu/templatetags/__init__.py
djangocms_custommenu/templatetags/custommenu_tags.py
djangocms_custommenu-1.0.3.dist-info/DESCRIPTION.rst
djangocms_custommenu-1.0.3.dist-info/METADATA
djangocms_custommenu-1.0.3.dist-info/RECORD
djangocms_custommenu-1.0.3.dist-info/WHEEL
djangocms_custommenu-1.0.3.dist-info/metadata.json
djangocms_custommenu-1.0.3.dist-info/top_level.txt
